bluew/__init__.py
bluew/api.py
bluew/characteristics.py
bluew/connections.py
bluew/controller.py
bluew/daemon.py
bluew/device.py
bluew/engine.py
bluew/errors.py
bluew/plugables.py
bluew/ppobj.py
bluew/rapid.py
bluew/services.py
bluew/utils.py
bluew/dbusted/__init__.py
bluew/dbusted/agent.py
bluew/dbusted/dbusted.py
bluew/dbusted/decorators.py
bluew/dbusted/interfaces.py
bluew/dbusted/utils.py
bluew-0.4.6.dist-info/DESCRIPTION.rst
bluew-0.4.6.dist-info/METADATA
bluew-0.4.6.dist-info/RECORD
bluew-0.4.6.dist-info/WHEEL
bluew-0.4.6.dist-info/metadata.json
bluew-0.4.6.dist-info/top_level.txt
