Metadata-Version: 2.0
Name: bluew
Version: 0.4.6
Summary: Bluetooth made easy.
Home-page: https://github.com/nullp0tr/Bluew
Author: Ahmed Alsharif (nullp0tr)
Author-email: ahmeds2000x@gmail.com
License: MIT
Keywords: bluetooth bluez BLE
Platform: UNKNOWN
Classifier: Development Status :: 3 - Alpha
Classifier: Intended Audience :: Developers
Classifier: Topic :: Software Development :: Build Tools
Classifier: License :: OSI Approved :: MIT License
Classifier: Programming Language :: Python :: 3
Classifier: Programming Language :: Python :: 3.2
Classifier: Programming Language :: Python :: 3.3
Classifier: Programming Language :: Python :: 3.4
Classifier: Programming Language :: Python :: 3.5
Classifier: Programming Language :: Python :: 3.6
Classifier: Programming Language :: Python :: 3.7
